[
  {
    "id": "f52ae2ed-9c7e-4aea-b24d-9fbe6b72cddb",
    "firstName": "Franco",
    "lastName": "Armani",
    "phoneNumber": "0500000002",
    "email": "farmani@petadoption.com",
    "password": "$2b$04$1wHacu1z6/xP/Q1cAaAB0OB.i6sa3YJaBQrRHqhw9FC3E6OaZxkoK",
    "confirmPassword": "$2b$04$VpQCj2M0l/X/mCIBIZCCHOy21xGb36YuY5gKCHy3lpPBRKeK.58y2",
    "createdDate": "2022-08-14T17:11:32.230Z"
  },
  {
    "id": "d5f614fc-ff51-4040-a96f-460921dae501",
    "firstName": "Lionel",
    "lastName": "Messi",
    "phoneNumber": "0500000001",
    "email": "lmessi@petadoption.com",
    "password": "$2b$04$N.mAEzZ.40diMqA5cu8ZH.tr3GzxS3fYiqjDqEfDkugPh.uxAQrvC",
    "confirmPassword": "$2b$04$D6M1TerFhV6a30APU9VEnukTuN/9MMlEyg6fAp7BeMtcj2heiPYvy",
    "createdDate": "2022-08-15T06:55:49.101Z"
  },
  {
    "id": "0037ff60-dc32-4796-b8fb-6c9f4d5fa20d",
    "firstName": "Roger",
    "lastName": "Federer",
    "phoneNumber": "0500000003",
    "email": "rfederer@petadoption.com",
    "password": "$2b$04$0fr1OFp.JtJ3OxkeMVMIAu0COl1JO.bjCRGexVeMxODnZNPlXeTfS",
    "confirmPassword": "$2b$04$rpGu0KU4F1edKatqQgGoNes5OVcZhYLmLLhd7V1KdZVUN2t3shkL.",
    "createdDate": "2022-08-16T11:31:08.937Z"
  },
  {
    "id": "5090e47a-5e4b-4fd5-b1f9-9291b56d3bde",
    "firstName": "Cristiano",
    "lastName": "Ronaldo",
    "phoneNumber": "0500000004",
    "email": "cronaldo@petadoption.com",
    "password": "$2b$04$9lrBORdDgJCAWcc1.ICBq..oGo8K.tqGOtnEPz9roTgpgJtzGzm5W",
    "confirmPassword": "$2b$04$4/Xw8xC2VeSKaA9fFcuXLu8rbEl52JcRdUM6.kFW167znCMEAmqJC",
    "createdDate": "2022-08-16T13:01:45.273Z"
  }
]
